mathnexus/__init__.py
mathnexus/coordinate_geometry.py
mathnexus/linear_datatypes.py
mathnexus/physics_visuals.py
mathnexus-0.3.8.dist-info/licenses/LICENSE
mathnexus-0.3.8.dist-info/METADATA
mathnexus-0.3.8.dist-info/WHEEL
mathnexus-0.3.8.dist-info/top_level.txt
mathnexus-0.3.8.dist-info/RECORD
