Metadata-Version: 2.4
Name: mathnexus
Version: 0.3.8
Summary: A pure Python library for Linear Algebra and 2D Geometry.
Home-page: https://github.com/Sidra-009/mathnexus
Author: Sidra Saqlain
Author-email: Sidra Saqlain <sidrasaqlain11@gmail.com>
License: MIT
Requires-Python: >=3.7
License-File: LICENSE
Dynamic: author
Dynamic: home-page
Dynamic: license-file
Dynamic: requires-python
